aioauth2/__init__.py
aioauth2-0.1.0.dist-info/LICENSE
aioauth2-0.1.0.dist-info/WHEEL
aioauth2-0.1.0.dist-info/METADATA
aioauth2-0.1.0.dist-info/RECORD
